api_requests.py
config.py
exceptions.py
main.py
utils.py
nutritionix_mcp_server-0.1.1.dist-info/METADATA
nutritionix_mcp_server-0.1.1.dist-info/WHEEL
nutritionix_mcp_server-0.1.1.dist-info/entry_points.txt
nutritionix_mcp_server-0.1.1.dist-info/licenses/LICENSE
nutritionix_mcp_server-0.1.1.dist-info/RECORD
