Metadata-Version: 2.4
Name: nutritionix-mcp-server
Version: 0.1.1
Summary: A MCP server for interacting with the Nutritionix API via Model Context Protocol tools
Author-email: Damyan Dimitrov <inspirationalcode@gmail.com>
Maintainer: MCP-FORGE
License: MIT
License-File: LICENSE
Keywords: ai,automation,llm,mcp,nutrition,nutritionix
Classifier: Development Status :: 4 - Beta
Classifier: Environment :: Console
Classifier: Intended Audience :: Developers
Classifier: License :: OSI Approved :: MIT License
Classifier: Operating System :: OS Independent
Classifier: Programming Language :: Python :: 3
Classifier: Programming Language :: Python :: 3.11
Classifier: Topic :: Software Development :: Libraries
Classifier: Topic :: Utilities
Requires-Python: >=3.11
Requires-Dist: black>=25.1.0
Requires-Dist: httpx>=0.28.1
Requires-Dist: mcp[cli]>=1.6.0
